raglink/__init__.py
raglink/configs/EmbedderConfig.py
raglink/configs/LlmConfig.py
raglink/configs/TestSplitterConfig.py
raglink/configs/VectorStoreConfig.py
raglink/configs/__init__.py
raglink/embeddings/EmbedderFactory.py
raglink/embeddings/__init__.py
raglink/embeddings/base.py
raglink/embeddings/doubao.py
raglink/embeddings/huggingface.py
raglink/embeddings/minimax.py
raglink/embeddings/modelscope.py
raglink/embeddings/openai.py
raglink/rag/DocumentLoaders.py
raglink/rag/__init__.py
raglink/rag/main.py
raglink/test_splitter/TestSplitterFactory.py
raglink/test_splitter/__init__.py
raglink/test_splitter/base.py
raglink/test_splitter/character.py
raglink/test_splitter/recursive_character.py
raglink/test_splitter/separator.py
raglink/utils/__init__.py
raglink/utils/config.py
raglink/utils/logger.py
raglink/utils/tools.py
raglink/vector_stores/VectorStoreFactory.py
raglink/vector_stores/__init__.py
raglink/vector_stores/base.py
raglink/vector_stores/milvus.py
raglink/vector_stores/milvus_test.py
raglink/vector_stores/qdrant.py
raglink-0.1.3.dist-info/METADATA
raglink-0.1.3.dist-info/WHEEL
raglink-0.1.3.dist-info/top_level.txt
raglink-0.1.3.dist-info/RECORD
