Metadata-Version: 2.4
Name: RAGLink
Version: 0.1.3
Summary: RAGLink是一个开源的Retrieval-Augmented Generation框架，旨在通过结合检索和大模型生成技术，提升自然语言处理任务的性能和效率。为用户提供了一个强大、灵活且易于扩展的开发环境。
Home-page: https://github.com/justinzm/RAGLink
Author: Justin ZM
Author-email: 3907721@qq.com
Maintainer: Justin ZM
Maintainer-email: 3907721@qq.com
License: MIT
Platform: all
Requires-Dist: langchain==0.3.25
Requires-Dist: langchain-community==0.3.24
Requires-Dist: loguru==0.7.2
Requires-Dist: pymilvus==2.5.10
Requires-Dist: python-dotenv==1.1.0
Requires-Dist: openpyxl==3.1.5
Requires-Dist: qdrant-client==1.10.1
Requires-Dist: docx2txt==0.8
Requires-Dist: sentence_transformers==4.1.0
Requires-Dist: datasets==2.18.0
Requires-Dist: modelscope==1.26.0
Requires-Dist: addict
Requires-Dist: torch
Requires-Dist: simplejson
Dynamic: author
Dynamic: author-email
Dynamic: description
Dynamic: description-content-type
Dynamic: home-page
Dynamic: license
Dynamic: maintainer
Dynamic: maintainer-email
Dynamic: platform
Dynamic: requires-dist
Dynamic: summary
